setup.py
whatstk/__init__.py
whatstk/core.py
whatstk/plot.py
whatstk/alpha/__init__.py
whatstk/alpha/data_extract.py
whatstk/alpha/exceptions.py
whatstk/alpha/parser.py
whatstk/learn/__init__.py
whatstk/learn/rnn.py
whatstk/learn/som.py
whatstk/learn/utils.py
whatstk-0.1.5.dist-info/LICENSE
whatstk-0.1.5.dist-info/METADATA
whatstk-0.1.5.dist-info/WHEEL
whatstk-0.1.5.dist-info/top_level.txt
whatstk-0.1.5.dist-info/RECORD
