Metadata-Version: 2.1
Name: whatstk
Version: 0.1.5
Summary: Parser and analytics tools for WhatsApp group chats
Home-page: http://github.com/lucasrodes/whatstk
Author: Lucas Rodes-Guirao
Author-email: hi@lcsrg.me
License: GPL-v3
Platform: UNKNOWN
Classifier: Development Status :: 3 - Alpha
Classifier: Programming Language :: Python :: 3
Classifier: License :: OSI Approved :: GNU General Public License v3 (GPLv3)
Classifier: Operating System :: OS Independent
Requires-Dist: pandas
Requires-Dist: numpy
Requires-Dist: plotly
